lan/__init__.py
lan/cli.py
lan/config.py
lan/filedb.py
lan/log.py
lan/mail.py
lan/monitor.py
lan/request.py
lan/test_loader.py
lan/utils.py
lan/yaml.py
lan/commands/__init__.py
lan/commands/create.py
lan/commands/make.py
lan/commands/pub.py
lan/commands/run.py
lan/commands/server.py
lan/commands/it/__init__.py
lan/commands/it/apis_tpl_code.py
lan/commands/it/config_apis_yaml.py
lan/commands/it/config_config_yaml.py
lan/commands/it/config_mail_yaml.py
lan/commands/it/config_repore_yaml.py
lan/commands/it/config_response_yaml.py
lan/commands/it/model_init.py
lan/commands/it/model_report.py
lan/commands/it/model_test.py
lan/commands/it/model_testrunner.py
lan/commands/it/model_tpl_chart.py
lan/commands/it/model_tpl_content.py
lan/commands/it/model_tpl_mail_html.py
lan/commands/it/model_tpl_nav.py
lan/commands/it/model_tpl_template.py
lan/commands/it/run.py
lan/commands/sm/__init__.py
lan/commands/sm/run.py
lan/commands/sm/templates_index.py
lan/commands/st/__init__.py
lan/commands/st/auth.py
lan/commands/st/main.py
lan/commands/st/run.py
lan/commands/st/task.py
lan.io-0.0.2.dist-info/LICENSE
lan.io-0.0.2.dist-info/METADATA
lan.io-0.0.2.dist-info/WHEEL
lan.io-0.0.2.dist-info/entry_points.txt
lan.io-0.0.2.dist-info/top_level.txt
lan.io-0.0.2.dist-info/RECORD
